{
	"info": {
		"_postman_id": "82342ea3-ccaf-4e79-ae21-dfc163c28501",
		"name": "Auth API",
		"schema": "https://schema.getpostman.com/json/collection/v2.1.0/collection.json",
		"_exporter_id": "39622485",
		"_collection_link": "https://sanskrit-pictionary.postman.co/workspace/Sanskrit-Pictionary-API-Testing~f23e56d7-d08d-4eca-a9de-9ea3a2564719/collection/39622485-82342ea3-ccaf-4e79-ae21-dfc163c28501?action=share&source=collection_link&creator=39622485"
	},
	"item": [
		{
			"name": "Register User",
			"event": [
				{
					"listen": "test",
					"script": {
						"exec": [
							"pm.test(\"Status code is 201\", function () {\r",
							"    pm.response.to.have.status(201);\r",
							"});\r",
							"\r",
							"pm.test(\"Message is 'User registered'\", function () {\r",
							"    const jsonData = pm.response.json();\r",
							"    pm.expect(jsonData.message).to.eql(\"User registered\");\r",
							"});\r",
							""
						],
						"type": "text/javascript",
						"packages": {}
					}
				}
			],
			"request": {
				"method": "POST",
				"header": [],
				"body": {
					"mode": "raw",
					"raw": "{\r\n  \"displayName\": \"Tony\",\r\n  \"email\": \"tonywu@gmail.com\",\r\n  \"password\": \"123456\"\r\n}",
					"options": {
						"raw": {
							"language": "json"
						}
					}
				},
				"url": {
					"raw": "{{base_url}}/auth/register",
					"host": [
						"{{base_url}}"
					],
					"path": [
						"auth",
						"register"
					]
				},
				"description": "Registers a new user with a display name, email, and password.\n\n**Method:** POST  \n**URL:** `{{base_url}}/api/auth/register`"
			},
			"response": []
		},
		{
			"name": "Login User",
			"event": [
				{
					"listen": "test",
					"script": {
						"exec": [
							"//Check if the status code is 200\r",
							"pm.test(\"Status code is 200\", function () {\r",
							"    pm.response.to.have.status(200);\r",
							"});\r",
							"\r",
							"//Check if the returned content contains the token\r",
							"pm.test(\"Response has token\", function () {\r",
							"    const jsonData = pm.response.json();\r",
							"    pm.expect(jsonData).to.have.property(\"token\");\r",
							"});\r",
							"\r",
							"//Check the user field structure\r",
							"pm.test(\"Response has user object with id and email\", function () {\r",
							"    const jsonData = pm.response.json();\r",
							"    pm.expect(jsonData.user).to.have.property(\"id\");\r",
							"    pm.expect(jsonData.user).to.have.property(\"email\");\r",
							"});"
						],
						"type": "text/javascript",
						"packages": {}
					}
				},
				{
					"listen": "prerequest",
					"script": {
						"exec": [
							"pm.request.headers.add({\r",
							"  key: 'Authorization',\r",
							"  value: `Bearer ${pm.environment.get(\"auth_token\")}`\r",
							"});"
						],
						"type": "text/javascript",
						"packages": {}
					}
				}
			],
			"request": {
				"method": "POST",
				"header": [],
				"body": {
					"mode": "raw",
					"raw": "{\r\n  \"email\": \"tonywu@gmail.com\",\r\n  \"password\": \"123456\"\r\n}",
					"options": {
						"raw": {
							"language": "json"
						}
					}
				},
				"url": {
					"raw": "{{base_url}}/auth/login",
					"host": [
						"{{base_url}}"
					],
					"path": [
						"auth",
						"login"
					]
				}
			},
			"response": [
				{
					"name": "Success - Login",
					"originalRequest": {
						"method": "POST",
						"header": [],
						"body": {
							"mode": "raw",
							"raw": "{\r\n  \"email\": \"tonywu@gmail.com\",\r\n  \"password\": \"123456\"\r\n}",
							"options": {
								"raw": {
									"language": "json"
								}
							}
						},
						"url": {
							"raw": "{{base_url}}/auth/login",
							"host": [
								"{{base_url}}"
							],
							"path": [
								"auth",
								"login"
							]
						}
					},
					"status": "OK",
					"code": 200,
					"_postman_previewlanguage": "json",
					"header": [
						{
							"key": "X-Powered-By",
							"value": "Express"
						},
						{
							"key": "Access-Control-Allow-Origin",
							"value": "*"
						},
						{
							"key": "Content-Type",
							"value": "application/json; charset=utf-8"
						},
						{
							"key": "Content-Length",
							"value": "306"
						},
						{
							"key": "ETag",
							"value": "W/\"132-GqFoDEmOesUY8raEW2nz1lf7Jto\""
						},
						{
							"key": "Date",
							"value": "Tue, 24 Jun 2025 07:46:14 GMT"
						},
						{
							"key": "Connection",
							"value": "keep-alive"
						},
						{
							"key": "Keep-Alive",
							"value": "timeout=5"
						}
					],
					"cookie": [],
					"body": "{\n    \"message\": \"Login successful\",\n    \"user\": {\n        \"id\": \"685a565e75e3100b25d935da\",\n        \"displayName\": \"Tony\",\n        \"email\": \"tonywu@gmail.com\"\n    },\n    \"token\": \"eyJhbGciOiJIUzI1NiIsInR5cCI6IkpXVCJ9.eyJ1c2VySWQiOiI2ODVhNTY1ZTc1ZTMxMDBiMjVkOTM1ZGEiLCJpYXQiOjE3NTA3NTExNzQsImV4cCI6MTc1MDc1ODM3NH0.I7aKqSlQqEHXEX2qEoB9rzHpmZhURxO11iU-Ic6oeEg\"\n}"
				},
				{
					"name": "Error - Invalid credentials",
					"originalRequest": {
						"method": "POST",
						"header": [],
						"body": {
							"mode": "raw",
							"raw": "{\r\n  \"email\": \"tonywu@gmail.com\",\r\n  \"password\": \"123457\"\r\n}",
							"options": {
								"raw": {
									"language": "json"
								}
							}
						},
						"url": {
							"raw": "{{base_url}}/auth/login",
							"host": [
								"{{base_url}}"
							],
							"path": [
								"auth",
								"login"
							]
						}
					},
					"status": "Unauthorized",
					"code": 401,
					"_postman_previewlanguage": "json",
					"header": [
						{
							"key": "X-Powered-By",
							"value": "Express"
						},
						{
							"key": "Access-Control-Allow-Origin",
							"value": "*"
						},
						{
							"key": "Content-Type",
							"value": "application/json; charset=utf-8"
						},
						{
							"key": "Content-Length",
							"value": "121"
						},
						{
							"key": "ETag",
							"value": "W/\"79-JXsSaTLD+0h4O3Zn1407Qrvg7vc\""
						},
						{
							"key": "Date",
							"value": "Tue, 24 Jun 2025 07:46:53 GMT"
						},
						{
							"key": "Connection",
							"value": "keep-alive"
						},
						{
							"key": "Keep-Alive",
							"value": "timeout=5"
						}
					],
					"cookie": [],
					"body": "{\n    \"success\": false,\n    \"errorCode\": \"ERR_CUSTOM\",\n    \"error\": \"Invalid password.\",\n    \"message\": \"The password you entered is incorrect.\"\n}"
				}
			]
		}
	],
	"event": [
		{
			"listen": "prerequest",
			"script": {
				"type": "text/javascript",
				"packages": {},
				"exec": [
					"if (pm.environment.get(\"token\")) {\r",
					"    pm.request.headers.add({\r",
					"        key: \"Authorization\",\r",
					"        value: \"Bearer \" + pm.environment.get(\"token\")\r",
					"    });\r",
					"}"
				]
			}
		},
		{
			"listen": "test",
			"script": {
				"type": "text/javascript",
				"packages": {},
				"exec": [
					""
				]
			}
		}
	]
}